careless/VERSION
careless/__init__.py
careless/careless.py
careless/parser.py
careless/args/__init__.py
careless/args/common.py
careless/args/crossvalidation.py
careless/args/filtration.py
careless/args/interpretation.py
careless/args/likelihood.py
careless/args/optimizer.py
careless/args/poly.py
careless/args/positional_encoding.py
careless/args/prior.py
careless/args/required.py
careless/args/scaling.py
careless/args/tf_options.py
careless/callbacks/__init__.py
careless/callbacks/progress_bar.py
careless/io/__init__.py
careless/io/asu.py
careless/io/formatter.py
careless/io/manager.py
careless/io/xds.py
careless/models/__init__.py
careless/models/base.py
careless/models/likelihoods/__init__.py
careless/models/likelihoods/base.py
careless/models/likelihoods/laue.py
careless/models/likelihoods/mono.py
careless/models/merging/__init__.py
careless/models/merging/surrogate_posteriors.py
careless/models/merging/variational.py
careless/models/priors/__init__.py
careless/models/priors/base.py
careless/models/priors/empirical.py
careless/models/priors/wilson.py
careless/models/scaling/__init__.py
careless/models/scaling/base.py
careless/models/scaling/image.py
careless/models/scaling/nn.py
careless/stats/__init__.py
careless/stats/ccanom.py
careless/stats/cchalf.py
careless/stats/ccpred.py
careless/stats/completeness.py
careless/stats/filter_by_image_cc.py
careless/stats/history.py
careless/stats/image_cc.py
careless/stats/isigi.py
careless/stats/parser.py
careless/stats/prior_b.py
careless/stats/rescale.py
careless/stats/rsplit.py
careless/utils/__init__.py
careless/utils/device.py
careless/utils/distributions.py
careless/utils/laue.py
careless/utils/positional_encoding.py
careless/utils/shame.py
careless-0.5.4.dist-info/licenses/LICENSE
careless-0.5.4.dist-info/METADATA
careless-0.5.4.dist-info/WHEEL
careless-0.5.4.dist-info/entry_points.txt
careless-0.5.4.dist-info/top_level.txt
careless-0.5.4.dist-info/RECORD
